README.md
neuralfields/__init__.py
neuralfields/custom_layers.py
neuralfields/custom_types.py
neuralfields/neural_fields.py
neuralfields/potential_based.py
neuralfields/simple_neural_fields.py
pyproject.toml
neuralfields-0.4.5.dist-info/LICENSE.txt
neuralfields-0.4.5.dist-info/METADATA
neuralfields-0.4.5.dist-info/WHEEL
neuralfields-0.4.5.dist-info/RECORD
