Metadata-Version: 2.1
Name: neuralfields
Version: 0.4.5
Summary: A type of potential-based recurrent neural networks implemented with PyTorch
Home-page: https://github.com/famura/neuralfields
License: MIT
Author: Fabio Muratore
Author-email: robot-learning@famura.net
Maintainer: Fabio Muratore
Maintainer-email: robot-learning@famura.net
Requires-Python: >=3.8,<4.0
Classifier: Development Status :: 4 - Beta
Classifier: Intended Audience :: Developers
Classifier: Intended Audience :: Science/Research
Classifier: License :: OSI Approved :: MIT License
Classifier: Natural Language :: English
Classifier: Programming Language :: Python :: 3
Classifier: Programming Language :: Python :: 3.8
Classifier: Programming Language :: Python :: 3.9
Classifier: Programming Language :: Python :: 3.10
Classifier: Programming Language :: Python :: 3.11
Classifier: Programming Language :: Python :: 3.12
Classifier: Programming Language :: Python :: 3.13
Requires-Dist: torch
Project-URL: Documentation, https://famura.github.io/neuralfields
Project-URL: Repository, https://github.com/famura/neuralfields
